superfunny/__init__.py
superfunny/command_line.py
superfunny-0.2.dist-info/LICENSE
superfunny-0.2.dist-info/METADATA
superfunny-0.2.dist-info/WHEEL
superfunny-0.2.dist-info/entry_points.txt
superfunny-0.2.dist-info/top_level.txt
superfunny-0.2.dist-info/RECORD
