Metadata-Version: 2.1
Name: superfunny
Version: 0.2
Summary: The funniest joke in the world
Home-page: http://github.com/melaniecheah/test_repo
Author: Melanie Cheah
Author-email: melaniecheah@example.com
License: MIT
Platform: UNKNOWN
License-File: LICENSE
Requires-Dist: markdown
